pybenutils/__init__.py
pybenutils/cli_tools.py
pybenutils/proxmox_utils.py
pybenutils/tests_files_utils.py
pybenutils/useful.py
pybenutils/windows_registry.py
pybenutils/amazon_boto3/__init__.py
pybenutils/amazon_boto3/amazon_obj.py
pybenutils/autogui/__init__.py
pybenutils/autogui/__main__.py
pybenutils/autogui/auto_gui_cls.py
pybenutils/browsers/__init__.py
pybenutils/browsers/chrome.py
pybenutils/browsers/firefox.py
pybenutils/browsers/selenium_utils.py
pybenutils/browsers/simple_browser_controller_cls.py
pybenutils/browsers/web_driver.py
pybenutils/browsers/windows_browsers_keywords.py
pybenutils/network/__init__.py
pybenutils/network/download_manager.py
pybenutils/network/http_cert_info.py
pybenutils/network/s3_bucket_cls.py
pybenutils/network/ssh_helper.py
pybenutils/network/ssh_utils.py
pybenutils/os_operations/__init__.py
pybenutils/os_operations/files_and_directories.py
pybenutils/os_operations/mac_application_control.py
pybenutils/os_operations/mac_input_control.py
pybenutils/os_operations/mac_operations.py
pybenutils/os_operations/mac_popup_handler.py
pybenutils/os_operations/process.py
pybenutils/os_operations/window_operations.py
pybenutils/utils_logger/__init__.py
pybenutils/utils_logger/config_logger.py
pybenutils-7.9.1.dist-info/licenses/LICENSE
webserver/pyserver.py
pybenutils-7.9.1.dist-info/METADATA
pybenutils-7.9.1.dist-info/WHEEL
pybenutils-7.9.1.dist-info/top_level.txt
pybenutils-7.9.1.dist-info/RECORD
