Metadata-Version: 2.4
Name: pybenutils
Version: 7.9.1
Summary: PyBEN Utilities repository contains a variety of useful methods and classes designed to allow easy access to high-level operations
Author: Ben Moskovitch
Author-email: Ben Moskovitch <darkflameben@gmail.com>
Maintainer-email: Ben Moskovitch <darkflameben@gmail.com>
License-Expression: MIT
Project-URL: Homepage, https://github.com/DarkFlameBEN/pybenutils.git
Keywords: python,proxmox,gui,utils,utilities,automation,automation-tools
Classifier: Development Status :: 5 - Production/Stable
Classifier: Intended Audience :: Developers
Classifier: Topic :: Software Development :: Libraries
Classifier: Operating System :: OS Independent
Classifier: Programming Language :: Python :: 3.8
Classifier: Programming Language :: Python :: 3.9
Classifier: Programming Language :: Python :: 3.10
Classifier: Programming Language :: Python :: 3.11
Classifier: Programming Language :: Python :: 3.12
Classifier: Programming Language :: Python :: 3.13
Requires-Python: >=3.8
License-File: LICENSE
Requires-Dist: requests>=2.32.5
Requires-Dist: supertools>=1.0.1
Requires-Dist: boto3>=1.42.15
Requires-Dist: psutil>=7.1.3
Requires-Dist: selenium>=4.39.0
Requires-Dist: multiprocess>=0.70.18
Requires-Dist: boto>=2.49.0
Requires-Dist: pysocks>=1.7.1
Requires-Dist: typing>=3.7.4.3
Requires-Dist: idna>=3.11
Requires-Dist: pyOpenSSL>=25.3.0
Requires-Dist: cryptography>=46.0.3
Requires-Dist: pyautogui>=0.9.54
Requires-Dist: looseversion>=1.3.0
Requires-Dist: scp>=0.15.0
Requires-Dist: Appium-Python-Client>=5.2.4
Requires-Dist: pyperclip>=1.11.0
Requires-Dist: pywin32>=311; sys_platform == "win32"
Requires-Dist: pypiwin32>=223; sys_platform == "win32"
Requires-Dist: pynput>=1.8.1; sys_platform != "linux"
Requires-Dist: paramiko>=4.0.0; platform_machine != "ARM64"
Requires-Dist: pywinauto>=0.6.9; sys_platform == "win32"
Dynamic: license-file
